cotools/__init__.py
cotools/data.py
cotools/hopkins.py
cotools/text.py
cord_19_tools-0.3.3.dist-info/LICENSE.txt
cord_19_tools-0.3.3.dist-info/METADATA
cord_19_tools-0.3.3.dist-info/WHEEL
cord_19_tools-0.3.3.dist-info/top_level.txt
cord_19_tools-0.3.3.dist-info/RECORD
