Metadata-Version: 2.1
Name: cord-19-tools
Version: 0.3.3
Summary: CORD 19 tools and utilities
Home-page: https://github.com/josephsdavid/cord-19-tools
Maintainer: David Josephs
Maintainer-email: josephsd@smu.edu
License: MIT
Platform: UNKNOWN
Classifier: Programming Language :: Python :: 3
Classifier: License :: OSI Approved :: MIT License
Classifier: Operating System :: OS Independent
Requires-Dist: xmltodict
